Partie_jeu/score_compteur/score_compteur.vhd
-- Créer un composant VHDL qui valide si le joueur appuie sur le bon bouton dans le temps imparti.
library ieee;
use ieee.std_logic_1164.all;
use ieee.numeric_std.all;

entity score_compteur is
    port (
        clk       : in  std_logic; -- horloge système
        reset     : in  std_logic; --remise à zéro du score
        valid_hit : in  std_logic; -- indiquant la réussite (1) ou l’échec (0)
        score     : out std_logic_vector(3 downto 0); -- score courant codé sur 4 bits
        game_over : out std_logic -- signal indiquant la fin du jeu
    );
end score_compteur;

architecture score_compteur_arch of score_compteur is
    signal score_reg : unsigned(3 downto 0) := (others => '0');
    signal game_over_resultat : std_logic := '0';
begin

     process(clk, reset)
    begin
        if reset = '1' then
            score_reg          <= (others => '0');
            game_over_resultat <= '0';

        elsif rising_edge(clk) then
            if game_over_resultat = '0' then
                if valid_hit = '1' then
                    if score_reg = to_unsigned(15, 4) then
                        -- Si on était déjà à 15, on signale game over
                        game_over_resultat <= '1';
                    else
                        -- Sinon, on incrémente
                        score_reg <= score_reg + 1;
                        if score_reg = to_unsigned(14, 4) then
                            -- On vient d’atteindre 15 → game over aussi
                            game_over_resultat <= '1';
                        end if;
                    end if;

                elsif valid_hit = '0' then
                    -- Faute : arrêt immédiat, on garde le score
                    game_over_resultat <= '1';
                end if;
            end if;
        end if;
    end process;

    score     <= std_logic_vector(score_reg);
    game_over <= game_over_resultat;

end score_compteur_arch;

score_compteur/score_compteur_testbench.vhd

library ieee;
use ieee.std_logic_1164.all;
use ieee.numeric_std.all;

entity score_compteur_tb is
end score_compteur_tb;

architecture score_compteur_tb_arch of score_compteur_tb is
    signal clk_sim       : std_logic := '0';
    signal reset_sim     : std_logic := '0';
    signal valid_hit_sim : std_logic := '0';
    signal score_sim         : std_logic_vector(3 downto 0);
    signal game_over_sim     : std_logic;

    component score_compteur
        port (
            clk       : in  std_logic;
            reset     : in  std_logic;
            valid_hit : in  std_logic;
            score     : out std_logic_vector(3 downto 0);
            game_over : out std_logic
        );
    end component;
begin

    score_inst: score_compteur
        port map (
            clk       => clk_sim,
            reset     => reset_sim,
            valid_hit => valid_hit_sim,
            score     => score_sim,
            game_over => game_over_sim
        );

    clk_process: process
    begin
        while now < 2 us loop
            clk_sim <= '0'; wait for 5 ns;
            clk_sim <= '1'; wait for 5 ns;
        end loop;
        wait;
    end process;

 
    score_proc: process
    begin
        -- Reset
        reset_sim <= '1';
        wait for 20 ns;
        reset_sim <= '0';

        -- 5 bonnes réponses
        for i in 1 to 5 loop
            valid_hit_sim <= '1';
            wait for 10 ns;
            valid_hit_sim <= '0';
            wait for 10 ns;
        end loop;

        -- 2 mauvaises réponses
        valid_hit_sim <= '0';
        wait for 30 ns;
        valid_hit_sim <= '0';
        wait for 30 ns;

        -- 10 bonnes réponses pour atteindre 15
        for i in 1 to 10 loop
            valid_hit_sim <= '1';
            wait for 10 ns;
            valid_hit_sim <= '0';
            wait for 10 ns;
        end loop;

        -- Encore une bonne réponse
        valid_hit_sim <= '1';
        wait for 10 ns;
        valid_hit_sim <= '0';
        wait for 10 ns;

        wait;
    end process;

    affichage: process(clk_sim)
    begin
        if rising_edge(clk_sim) then
            
                report "score=" & integer'image(to_integer(unsigned(score_sim)))
                    & " | game_over=" & std_logic'image(game_over_sim)
                    & " | valid_hit=" & std_logic'image(valid_hit_sim);
       
        end if;
    end process;

end  score_compteur_tb_arch;

Partie_jeu/score_compteur/score_compteur_gtkwave.vcd
$date
  Mon Jun  2 17:54:50 2025
$end
$version
  GHDL v0
$end
$timescale
  1 fs
$end
$scope module standard $end
$upscope $end
$scope module std_logic_1164 $end
$upscope $end
$scope module numeric_std $end
$upscope $end
$scope module score_compteur_tb $end
$var reg 1 ! clk_sim $end
$var reg 1 " reset_sim $end
$var reg 1 # valid_hit_sim $end
$var reg 4 $ score_sim[3:0] $end
$var reg 1 % game_over_sim $end
$scope module score_inst $end
$var reg 1 & clk $end
$var reg 1 ' reset $end
$var reg 1 ( valid_hit $end
$var reg 4 ) score[3:0] $end
$var reg 1 * game_over $end
$var reg 4 + score_reg[3:0] $end
$var reg 1 , game_over_resultat $end
$upscope $end
$upscope $end
$enddefinitions $end
#0
0!
1"
0#
b0000 $
0%
0&
1'
0(
b0000 )
0*
b0000 +
0,
#5000000
1!
1&
#10000000
0!
0&
#15000000
1!
1&
#20000000
0!
0"
1#
0&
0'
1(
#25000000
1!
b0001 $
1&
b0001 )
b0001 +
#30000000
0!
0#
0&
0(
#35000000
1!
1%
1&
1*
1,
#40000000
0!
1#
0&
1(
#45000000
1!
1&
#50000000
0!
0#
0&
0(
#55000000
1!
1&
#60000000
0!
1#
0&
1(
#65000000
1!
1&
#70000000
0!
0#
0&
0(
#75000000
1!
1&
#80000000
0!
1#
0&
1(
#85000000
1!
1&
#90000000
0!
0#
0&
0(
#95000000
1!
1&
#100000000
0!
1#
0&
1(
#105000000
1!
1&
#110000000
0!
0#
0&
0(
#115000000
1!
1&
#120000000
0!
0&
#125000000
1!
1&
#130000000
0!
0&
#135000000
1!
1&
#140000000
0!
0&
#145000000
1!
1&
#150000000
0!
0&
#155000000
1!
1&
#160000000
0!
0&
#165000000
1!
1&
#170000000
0!
0&
#175000000
1!
1&
#180000000
0!
1#
0&
1(
#185000000
1!
1&
#190000000
0!
0#
0&
0(
#195000000
1!
1&
#200000000
0!
1#
0&
1(
#205000000
1!
1&
#210000000
0!
0#
0&
0(
#215000000
1!
1&
#220000000
0!
1#
0&
1(
#225000000
1!
1&
#230000000
0!
0#
0&
0(
#235000000
1!
1&
#240000000
0!
1#
0&
1(
#245000000
1!
1&
#250000000
0!
0#
0&
0(
#255000000
1!
1&
#260000000
0!
1#
0&
1(
#265000000
1!
1&
#270000000
0!
0#
0&
0(
#275000000
1!
1&
#280000000
0!
1#
0&
1(
#285000000
1!
1&
#290000000
0!
0#
0&
0(
#295000000
1!
1&
#300000000
0!
1#
0&
1(
#305000000
1!
1&
#310000000
0!
0#
0&
0(
#315000000
1!
1&
#320000000
0!
1#
0&
1(
#325000000
1!
1&
#330000000
0!
0#
0&
0(
#335000000
1!
1&
#340000000
0!
1#
0&
1(
#345000000
1!
1&
#350000000
0!
0#
0&
0(
#355000000
1!
1&
#360000000
0!
1#
0&
1(
#365000000
1!
1&
#370000000
0!
0#
0&
0(
#375000000
1!
1&
#380000000
0!
1#
0&
1(
#385000000
1!
1&
#390000000
0!
0#
0&
0(
