hearth_ual/hearth_ual.vhd
library ieee;
use ieee.std_logic_1164.all;
use ieee.std_logic_signed.all;  

entity hearth_ual is
    port(
        A        : in  std_logic_vector(3 downto 0);
        B        : in  std_logic_vector(3 downto 0);
        SR_IN_L  : in  std_logic;                    -- bit de retenue d'entrée pour décalage à droite
        SR_IN_R  : in  std_logic;                    -- bit de retenue d'entrée pour décalage à gauche et addition

        SEL_FCT  : in  std_logic_vector(3 downto 0); -- SEL_FCT est le code de la fonction à réaliser

        SR_OUT_L : out std_logic;                    -- bit de retenue de sortie gauche
        SR_OUT_R : out std_logic;                    -- bit de retenue de sortie droite
        S        : out std_logic_vector(7 downto 0)   -- résultat ALU 8 bits
    );
end hearth_ual;

architecture hearth_ual_arch of hearth_ual is
begin
    myUALProcess : process(A, B, SR_IN_L, SR_IN_R, SEL_FCT)
        -- Variables internes
        variable grand_A         : std_logic_vector(7 downto 0);
        variable grand_B         : std_logic_vector(7 downto 0);
        variable carry_in_left   : std_logic;
        variable carry_in_right  : std_logic;
        variable carry_out_left  : std_logic;
        variable carry_out_right : std_logic;
        variable resultat        : std_logic_vector(7 downto 0);
    begin

        -- Extension de signe pour A et B (4 bits à 8 bits)
        grand_A(7 downto 4) := (others => A(3));
        grand_A(3 downto 0) := A;
        grand_B(7 downto 4) := (others => B(3));
        grand_B(3 downto 0) := B;
        
        -- Récupération des retenues d'entrée
        carry_in_left  := SR_IN_L;
        carry_in_right := SR_IN_R;
        
        -- Valeurs par défaut
        carry_out_left  := '0';
        carry_out_right := '0';
        resultat        := (others => '0');

        case SEL_FCT is

            when "0000" => -- nop (no operation) S = 0 | SR_OUT_L = 0 et SR_OUT_R = 0
                null;
            when "0001" => -- S = A | SR_OUT_L = 0 et SR_OUT_R = 0
                resultat      := "0000" & A;
            when "0010" => -- S = B | SR_OUT_L = 0 et SR_OUT_R = 0
                resultat      := "0000" & B;
            when "0011" => -- S = not A | SR_OUT_L = 0 et SR_OUT_R = 0
                resultat      := "0000" & not A;
            when "0100" => -- S = not B | SR_OUT_L = 0 et SR_OUT_R = 0
                resultat      := "0000" & not B;
            when "0101" => -- S = A and B | SR_OUT_L = 0 et SR_OUT_R = 0
                resultat      := "0000" & (A and B);
            when "0110" => -- S = A or B | SR_OUT_L = 0 et SR_OUT_R = 0
                resultat      := "0000" & (A or B);
            when "0111" => -- S = A xor B | SR_OUT_L = 0 et SR_OUT_R = 0
                resultat      := "0000" & (A xor B);
            when "1000" => -- S = Déc. droite A sur 4 bits (avec SR_IN_L) | SR_IN_L pour le bit entrant et SR_OUT_R pour le bit sortant
                resultat(2 downto 0) := A(3 downto 1);
                resultat(3)          := carry_in_left;
                carry_out_right      := A(0);
            when "1001" => -- S = Déc. gauche A sur 4 bits (avec SR_IN_R) | SR_IN_R pour le bit entrant et SR_OUT_L pour le bit sortant
                resultat(3 downto 1) := A(2 downto 0);
                resultat(0)          := carry_in_right;
                carry_out_left       := A(3);
            when "1010" => -- S = Déc. droite B sur 4 bits (avec SR_IN_L) | SR_IN_L pour le bit entrant et SR_OUT_R pour le bit sortant
                resultat(2 downto 0) := B(3 downto 1);
                resultat(3)          := carry_in_left;
                carry_out_right      := B(0);
            when "1011" => -- S = Déc. gauche B sur 4 bits (avec SR_IN_R) | SR_IN_R pour le bit entrant et SR_OUT_L pour le bit sortant
                resultat(3 downto 1) := B(2 downto 0);
                resultat(0)          := carry_in_right;
                carry_out_left       := B(3);
           
            when "1100" =>  -- S = A + B avec retenue d'entrée (SR_IN_R)
                resultat      := grand_A + grand_B + ("0000000" & carry_in_right);
            when "1101" =>  -- S = A + B sans retenue d'entrée
                resultat      := grand_A + grand_B;
            when "1110" =>  -- S = A - B (soustraction binaire)
                resultat      := grand_A - grand_B;
            when "1111" =>  -- S = A * B (multiplication binaire)
                resultat      := A * B;
            when others =>
                resultat      := (others => '0');
        end case;
        -- Assignation des sorties
        S        <= resultat;
        SR_OUT_L <= carry_out_left;
        SR_OUT_R <= carry_out_right;
    end process myUALProcess;
end hearth_ual_arch;

ual/ual_testbench.vhd
-- Testbench complet corrigé pour Hearth_UAL avec affichage en décimal

library ieee;
use ieee.std_logic_1164.all;
use ieee.numeric_std.all;

entity hearth_ual_tb is
end entity;

architecture hearth_ual_tb_arch of hearth_ual_tb is

    component hearth_ual is
        port (
            A        : in  std_logic_vector(3 downto 0);
            B        : in  std_logic_vector(3 downto 0);
            SR_IN_L  : in  std_logic;
            SR_IN_R  : in  std_logic;
            SEL_FCT  : in  std_logic_vector(3 downto 0);
            SR_OUT_L : out std_logic;
            SR_OUT_R : out std_logic;
            S        : out std_logic_vector(7 downto 0)
        );
    end component;

    signal A_sim, B_sim      : std_logic_vector(3 downto 0) := (others => '0');
    signal SR_IN_L_sim     : std_logic := '0';
    signal SR_IN_R_sim     : std_logic := '0';
    signal SEL_sim         : std_logic_vector(3 downto 0) := (others => '0');
    signal SR_OUT_L_sim    : std_logic;
    signal SR_OUT_R_sim    : std_logic;
    signal S_sim           : std_logic_vector(7 downto 0);

begin

    hearth_ual_inst: hearth_ual
        port map (
            A        => A_sim,
            B        => B_sim,
            SR_IN_L  => SR_IN_L_sim,
            SR_IN_R  => SR_IN_R_sim,
            SEL_FCT  => SEL_sim,
            SR_OUT_L => SR_OUT_L_sim,
            SR_OUT_R => SR_OUT_R_sim,
            S        => S_sim
        );

    stim_proc: process
        procedure display_case(name : string) is
        begin
            report "Test: " & name & " | A=" & integer'image(to_integer(unsigned(A_sim))) &
                   " B=" & integer'image(to_integer(unsigned(B_sim))) &
                   " SR_IN_L=" & std_logic'image(SR_IN_L_sim) &
                   " SR_IN_R=" & std_logic'image(SR_IN_R_sim) &
                   " SEL_FCT=" & integer'image(to_integer(unsigned(SEL_sim))) &
                   " S=" & integer'image(to_integer(unsigned(S_sim))) &
                   " SR_OUT_L=" & std_logic'image(SR_OUT_L_sim) &
                   " SR_OUT_R=" & std_logic'image(SR_OUT_R_sim);
        end procedure;

        procedure test_case(
            signal_name : string;
            sel_val     : std_logic_vector(3 downto 0);
            a_val, b_val : std_logic_vector(3 downto 0);
            sr_in_l, sr_in_r : std_logic;
            expected_Sim  : std_logic_vector(7 downto 0);
            expected_L, expected_R : std_logic := '0'
        ) is
        begin
            SEL_sim <= sel_val;
            A_sim <= a_val;
            B_sim <= b_val;
            SR_IN_L_sim <= sr_in_l;
            SR_IN_R_sim <= sr_in_r;
            wait for 10 ns;
            display_case(signal_name);
            assert S_sim = expected_Sim report signal_name & ": S incorrect" severity error;
            assert SR_OUT_L_sim = expected_L report signal_name & ": SR_OUT_L incorrect" severity error;
            assert SR_OUT_R_sim = expected_R report signal_name & ": SR_OUT_R incorrect" severity error;
        end procedure;

    begin

        test_case("NOP",        "0000", "0000", "0000", '0', '0', (others => '0'));
        test_case("S=A",        "0001", "0010", "0000", '0', '0', "00000010");
        test_case("S=B",        "0010", "0000", "0011", '0', '0', "00000011");
        test_case("S=not A",    "0011", "0101", "0000", '0', '0', "00001010");
        test_case("S=not B",    "0100", "0000", "1001", '0', '0', "00000110");
        test_case("S=A and B",  "0101", "0110", "0101", '0', '0', "00000100");
        test_case("S=A or B",   "0110", "0100", "0011", '0', '0', "00000111");
        test_case("S=A xor B",  "0111", "0111", "0010", '0', '0', "00000101");

        test_case("Shift droit A", "1000", "1010", "0000", '1', '0', "00001101", '0', '0');
        SR_IN_L_sim <= '0';

        test_case("Shift gauche A", "1001", "1100", "0000", '0', '1', "00001001", '1', '0');
        SR_IN_R_sim <= '0';

        test_case("Shift droit B", "1010", "0000", "0110", '1', '0', "00001011", '0', '0');
        SR_IN_L_sim <= '0';

        test_case("Shift gauche B", "1011", "0000", "0011", '0', '1', "00000111", '0', '0');
        SR_IN_R_sim <= '0';

        test_case("Addition A+B+SR_IN_R", "1100", "0010", "0011", '0', '1', "00000110");
        SR_IN_R_sim <= '0';

        test_case("Addition A+B", "1101", "0100", "0010", '0', '0', "00000110");
        test_case("Soustraction A-B", "1110", "0111", "0011", '0', '0', "00000100");

        report "Tous les tests passés avec succès." severity note;
        wait;

    end process;

end architecture hearth_ual_tb_arch;

hearth_ual/hearth_ual_gtkwave.vcd
$date
  Mon May 26 20:23:41 2025
$end
$version
  GHDL v0
$end
$timescale
  1 fs
$end
$scope module standard $end
$upscope $end
$scope module std_logic_1164 $end
$upscope $end
$scope module numeric_std $end
$upscope $end
$scope module std_logic_arith $end
$upscope $end
$scope module std_logic_signed $end
$upscope $end
$scope module hearth_ual_tb $end
$var reg 4 ! a_sim[3:0] $end
$var reg 4 " b_sim[3:0] $end
$var reg 1 # sr_in_l_sim $end
$var reg 1 $ sr_in_r_sim $end
$var reg 4 % sel_sim[3:0] $end
$var reg 1 & sr_out_l_sim $end
$var reg 1 ' sr_out_r_sim $end
$var reg 8 ( s_sim[7:0] $end
$scope module hearth_ual_inst $end
$var reg 4 ) a[3:0] $end
$var reg 4 * b[3:0] $end
$var reg 1 + sr_in_l $end
$var reg 1 , sr_in_r $end
$var reg 4 - sel_fct[3:0] $end
$var reg 1 . sr_out_l $end
$var reg 1 / sr_out_r $end
$var reg 8 0 s[7:0] $end
$upscope $end
$upscope $end
$enddefinitions $end
#0
b0000 !
b0000 "
0#
0$
b0000 %
0&
0'
b00000000 (
b0000 )
b0000 *
0+
0,
b0000 -
0.
0/
b00000000 0
#10000000
b0010 !
b0001 %
b00000010 (
b0010 )
b0001 -
b00000010 0
#20000000
b0000 !
b0011 "
b0010 %
b00000011 (
b0000 )
b0011 *
b0010 -
b00000011 0
#30000000
b0101 !
b0000 "
b0011 %
b00001010 (
b0101 )
b0000 *
b0011 -
b00001010 0
#40000000
b0000 !
b1001 "
b0100 %
b00000110 (
b0000 )
b1001 *
b0100 -
b00000110 0
#50000000
b0110 !
b0101 "
b0101 %
b00000100 (
b0110 )
b0101 *
b0101 -
b00000100 0
#60000000
b0100 !
b0011 "
b0110 %
b00000111 (
b0100 )
b0011 *
b0110 -
b00000111 0
#70000000
b0111 !
b0010 "
b0111 %
b00000101 (
b0111 )
b0010 *
b0111 -
b00000101 0
#80000000
b1010 !
b0000 "
1#
b1000 %
b00001101 (
b1010 )
b0000 *
1+
b1000 -
b00001101 0
#90000000
b1100 !
0#
1$
b1001 %
1&
b00001001 (
b1100 )
0+
1,
b1001 -
1.
b00001001 0
#100000000
b0000 !
b0110 "
1#
0$
b1010 %
0&
b00001011 (
b0000 )
b0110 *
1+
0,
b1010 -
0.
b00001011 0
#110000000
b0011 "
0#
1$
b1011 %
b00000111 (
b0011 *
0+
1,
b1011 -
b00000111 0
#120000000
b0010 !
b1100 %
b00000110 (
b0010 )
b1100 -
b00000110 0
#130000000
b0100 !
b0010 "
0$
b1101 %
b0100 )
b0010 *
0,
b1101 -
#140000000
b0111 !
b0011 "
b1110 %
b00000100 (
b0111 )
b0011 *
b1110 -
b00000100 0
