Partie_jeu/minuteur/minuteur.vhd
library ieee;
use ieee.std_logic_1164.all;
use ieee.numeric_std.all;

entity minuteur is 
    port (
        clk      : in std_logic;
        reset    : in std_logic;
        start    : in std_logic;
        sw_level : in std_logic_vector(1 downto 0);
        time_out : out std_logic
    );
end minuteur;

architecture minuteur_arch of minuteur is
    signal counter     : unsigned(26 downto 0) := (others => '0');
    signal running     : std_logic := '0';
    signal timeout_resultat : std_logic := '0';
    signal limit       : unsigned(26 downto 0);
begin

    -- Affectation concurrente de limit (toujours à jour)
    with sw_level select
        limit <= to_unsigned(100_000_000-1, 27) when "00",
                 to_unsigned(50_000_000-1, 27)  when "01",
                 to_unsigned(25_000_000-1, 27)  when "10",
                 to_unsigned(12_500_000-1, 27)  when others;

    process(clk, reset)
    begin
        if reset = '1' then
            counter     <= (others => '0');
            running     <= '0';
            timeout_resultat <= '0';
        elsif rising_edge(clk) then
            if start = '1' and running = '0' then
                running     <= '1';
                counter     <= (others => '0');
                timeout_resultat <= '0';
            elsif running = '1' then
                if counter < limit then
                    counter <= counter + 1;
                else
                    timeout_resultat <= '1';
                    running     <= '0';
                end if;
            else
                timeout_resultat <= '0';
            end if;
        end if;
    end process;

    time_out <= timeout_resultat;

end minuteur_arch;

minuteur/minuteur_testbench.vhd
library ieee;
use ieee.std_logic_1164.all;
use ieee.numeric_std.all;

entity minuteur_tb is
end minuteur_tb;

architecture minuteur_tb_arch of minuteur_tb is
    signal clk_sim      : std_logic := '0';
    signal reset_sim    : std_logic := '0';
    signal start_sim    : std_logic := '0';
    signal sw_level_sim : std_logic_vector(1 downto 0) := "00";
    signal time_out_sim : std_logic;

    component minuteur
        port (
            clk      : in  std_logic;
            reset    : in  std_logic;
            start    : in  std_logic;
            sw_level : in  std_logic_vector(1 downto 0);
            time_out : out std_logic
        );
    end component;
    function slv_to_str(slv : std_logic_vector) return string is
        variable result : string(1 to slv'length);
    begin
        for i in slv'range loop
            result(i - slv'low + 1) := character'VALUE(std_ulogic'image(slv(i)));
        end loop;
        return result;
    end function;
begin

    minuteur_inst: minuteur
        port map (
            clk      => clk_sim,
            reset    => reset_sim,
            start    => start_sim,
            sw_level => sw_level_sim,
            time_out => time_out_sim
        );

    -- Génération de l'horloge 100 MHz (période 10 ns)
    clk_process: process
    begin
        while now < 2 ms loop
            clk_sim <= '0'; wait for 5 ns;
            clk_sim <= '1'; wait for 5 ns;
        end loop;
        wait;
    end process;

    -- Stimulus principal
    minuteur_proc: process
    begin
        -- Reset initial
        reset_sim <= '1';
        wait for 20 ns;
        reset_sim <= '0';

        -- Test niveau 00 (1s)
        sw_level_sim <= "00";
        start_sim <= '1';
        wait for 10 ns;
        start_sim <= '0';

        wait for 1.1 sec; -- attendre plus que le timeout

        -- Test niveau 01 (0.5s)
        sw_level_sim <= "01";
        start_sim <= '1';
        wait for 10 ns;
        start_sim <= '0';

        wait for 0.6 sec;

        -- Test niveau 10 (0.25s)
        sw_level_sim <= "10";
        start_sim <= '1';
        wait for 10 ns;
        start_sim <= '0';

        wait for 0.3 sec;

        -- Test niveau 11 (0.125s)
        sw_level_sim <= "11";
        start_sim <= '1';
        wait for 10 ns;
        start_sim <= '0';

        wait for 0.2 sec;

        wait;
    end process;

affichage: process(clk_sim)
begin
    if rising_edge(clk_sim) then
        report "t=" & time'image(now) &
               " | reset=" & std_logic'image(reset_sim) &
               " | start=" & std_logic'image(start_sim) &
               " | sw_level=" & slv_to_str(sw_level_sim) &
               " | time_out=" & std_logic'image(time_out_sim);
    end if;
end process;

end minuteur_tb_arch;

Partie_jeu/minuteur/minuteur_gtkwave.vcd
$date
  Wed May 28 23:04:42 2025
$end
$version
  GHDL v0
$end
$timescale
  1 fs
$end
$scope module standard $end
$upscope $end
$scope module std_logic_1164 $end
$upscope $end
$scope module numeric_std $end
$upscope $end
$scope module minuteur_tb $end
$var reg 1 ! clk_sim $end
$var reg 1 " reset_sim $end
$var reg 1 # start_sim $end
$var reg 2 $ sw_level_sim[1:0] $end
$var reg 1 % time_out_sim $end
$scope module minuteur_inst $end
$var reg 1 & clk $end
$var reg 1 ' reset $end
$var reg 1 ( start $end
$var reg 2 ) sw_level[1:0] $end
$var reg 1 * time_out $end
$var reg 27 + counter[26:0] $end
$var reg 1 , running $end
$var reg 1 - timeout_resultat $end
$var reg 27 . limit[26:0] $end
$upscope $end
$upscope $end
$enddefinitions $end
#0
0!
1"
0#
b11 $
0%
0&
1'
0(
b11 )
0*
b000000000000000000000000000 +
0,
0-
b000101111101011110000011111 .
#5000000
1!
1&
#10000000
0!
0&
#15000000
1!
1&
#20000000
0!
0"
1#
0&
0'
1(
#25000000
1!
1&
1,
#30000000
0!
0#
0&
0(
#35000000
1!
1&
b000000000000000000000000001 +
#40000000
0!
0&
#45000000
1!
1&
b000000000000000000000000010 +
#50000000
0!
0&
#55000000
1!
1&
b000000000000000000000000011 +
#60000000
0!
0&
#65000000
1!
1&
b000000000000000000000000100 +
#70000000
0!
0&
#75000000
1!
1&
b000000000000000000000000101 +
#80000000
0!
0&
#85000000
1!
1&
b000000000000000000000000110 +
#90000000
0!
0&
#95000000
1!
1&
b000000000000000000000000111 +
#100000000
0!
0&
#105000000
1!
1&
b000000000000000000000001000 +
#110000000
0!
0&
#115000000
1!
1&
b000000000000000000000001001 +
#120000000
0!
0&
#125000000
1!
1&
b000000000000000000000001010 +
#130000000
0!
0&
#135000000
1!
1&
b000000000000000000000001011 +
#140000000
0!
0&
#145000000
1!
1&
b000000000000000000000001100 +
#150000000
0!
0&
#155000000
1!
1&
b000000000000000000000001101 +
#160000000
0!
0&
#165000000
1!
1&
b000000000000000000000001110 +
#170000000
0!
0&
#175000000
1!
1&
b000000000000000000000001111 +
#180000000
0!
0&
#185000000
1!
1&
b000000000000000000000010000 +
#190000000
0!
0&
#195000000
1!
1&
b000000000000000000000010001 +
#200000000
0!
0&
#205000000
1!
1&
b000000000000000000000010010 +
#210000000
0!
0&
#215000000
1!
1&
b000000000000000000000010011 +
#220000000
0!
0&
#225000000
1!
1&
b000000000000000000000010100 +
#230000000
0!
0&
#235000000
1!
1&
b000000000000000000000010101 +
#240000000
0!
0&
#245000000
1!
1&
b000000000000000000000010110 +
#250000000
0!
0&
#255000000
1!
1&
b000000000000000000000010111 +
#260000000
0!
0&
#265000000
1!
1&
b000000000000000000000011000 +
#270000000
0!
0&
#275000000
1!
1&
b000000000000000000000011001 +
#280000000
0!
0&
#285000000
1!
1&
b000000000000000000000011010 +
#290000000
0!
0&
#295000000
1!
1&
b000000000000000000000011011 +
#300000000
0!
0&
#305000000
1!
1&
b000000000000000000000011100 +
#310000000
0!
0&
#315000000
1!
1&
b000000000000000000000011101 +
#320000000
0!
0&
#325000000
1!
1&
b000000000000000000000011110 +
#330000000
0!
0&
#335000000
1!
1&
b000000000000000000000011111 +
#340000000
0!
0&
#345000000
1!
1&
b000000000000000000000100000 +
#350000000
0!
0&
#355000000
1!
1&
b000000000000000000000100001 +
#360000000
0!
0&
#365000000
1!
1&
b000000000000000000000100010 +
#370000000
0!
0&
#375000000
1!
1&
b000000000000000000000100011 +
#380000000
0!
0&
#385000000
1!
1&
b000000000000000000000100100 +
#390000000
0!
0&
#395000000
1!
1&
b000000000000000000000100101 +
#400000000
0!
0&
#405000000
1!
1&
b000000000000000000000100110 +
#410000000
0!
0&
#415000000
1!
1&
b000000000000000000000100111 +
#420000000
0!
0&
#425000000
1!
1&
b000000000000000000000101000 +
#430000000
0!
0&
#435000000
1!
1&
b000000000000000000000101001 +
#440000000
0!
0&
#445000000
1!
1&
b000000000000000000000101010 +
#450000000
0!
0&
#455000000
1!
1&
b000000000000000000000101011 +
#460000000
0!
0&
#465000000
1!
1&
b000000000000000000000101100 +
#470000000
0!
0&
#475000000
1!
1&
b000000000000000000000101101 +
#480000000
0!
0&
#485000000
1!
1&
b000000000000000000000101110 +
#490000000
0!
0&
#495000000
1!
1&
b000000000000000000000101111 +
#500000000
0!
0&
#505000000
1!
1&
b000000000000000000000110000 +
#510000000
0!
0&
#515000000
1!
1&
b000000000000000000000110001 +
#520000000
0!
0&
#525000000
1!
1&
b000000000000000000000110010 +
#530000000
0!
0&
#535000000
1!
1&
b000000000000000000000110011 +
#540000000
0!
0&
#545000000
1!
1&
b000000000000000000000110100 +
#550000000
0!
0&
#555000000
1!
1&
b000000000000000000000110101 +
#560000000
0!
0&
#565000000
1!
1&
b000000000000000000000110110 +
#570000000
0!
0&
#575000000
1!
1&
b000000000000000000000110111 +
#580000000
0!
0&
#585000000
1!
1&
b000000000000000000000111000 +
#590000000
0!
0&
#595000000
1!
1&
b000000000000000000000111001 +
#600000000
0!
0&
#605000000
1!
1&
b000000000000000000000111010 +
#610000000
0!
0&
#615000000
1!
1&
b000000000000000000000111011 +
#620000000
0!
0&
#625000000
1!
1&
b000000000000000000000111100 +
#630000000
0!
0&
#635000000
1!
1&
b000000000000000000000111101 +
#640000000
0!
0&
#645000000
1!
1&
b000000000000000000000111110 +
#650000000
0!
0&
#655000000
1!
1&
b000000000000000000000111111 +
#660000000
0!
0&
#665000000
1!
1&
b000000000000000000001000000 +
#670000000
0!
0&
#675000000
1!
1&
b000000000000000000001000001 +
#680000000
0!
0&
#685000000
1!
1&
b000000000000000000001000010 +
#690000000
0!
0&
#695000000
1!
1&
b000000000000000000001000011 +
#700000000
0!
0&
#705000000
1!
1&
b000000000000000000001000100 +
#710000000
0!
0&
#715000000
1!
1&
b000000000000000000001000101 +
#720000000
0!
0&
#725000000
1!
1&
b000000000000000000001000110 +
#730000000
0!
0&
#735000000
1!
1&
b000000000000000000001000111 +
#740000000
0!
0&
#745000000
1!
1&
b000000000000000000001001000 +
#750000000
0!
0&
#755000000
1!
1&
b000000000000000000001001001 +
#760000000
0!
0&
#765000000
1!
1&
b000000000000000000001001010 +
#770000000
0!
0&
#775000000
1!
1&
b000000000000000000001001011 +
#780000000
0!
0&
#785000000
1!
1&
b000000000000000000001001100 +
#790000000
0!
0&
#795000000
1!
1&
b000000000000000000001001101 +
#800000000
0!
0&
#805000000
1!
1&
b000000000000000000001001110 +
#810000000
0!
0&
#815000000
1!
1&
b000000000000000000001001111 +
#820000000
0!
0&
#825000000
1!
1&
b000000000000000000001010000 +
#830000000
0!
0&
#835000000
1!
1&
b000000000000000000001010001 +
#840000000
0!
0&
#845000000
1!
1&
b000000000000000000001010010 +
#850000000
0!
0&
#855000000
1!
1&
b000000000000000000001010011 +
#860000000
0!
0&
#865000000
1!
1&
b000000000000000000001010100 +
#870000000
0!
0&
#875000000
1!
1&
b000000000000000000001010101 +
#880000000
0!
0&
#885000000
1!
1&
b000000000000000000001010110 +
#890000000
0!
0&
#895000000
1!
1&
b000000000000000000001010111 +
#900000000
0!
0&
#905000000
1!
1&
b000000000000000000001011000 +
#910000000
0!
0&
#915000000
1!
1&
b000000000000000000001011001 +
#920000000
0!
0&
#925000000
1!
1&
b000000000000000000001011010 +
#930000000
0!
0&
#935000000
1!
1&
b000000000000000000001011011 +
#940000000
0!
0&
#945000000
1!
1&
b000000000000000000001011100 +
#950000000
0!
0&
#955000000
1!
1&
b000000000000000000001011101 +
#960000000
0!
0&
#965000000
1!
1&
b000000000000000000001011110 +
#970000000
0!
0&
#975000000
1!
1&
b000000000000000000001011111 +
#980000000
0!
0&
#985000000
1!
1&
b000000000000000000001100000 +
#990000000
0!
0&
#995000000
1!
1&
b000000000000000000001100001 +
#1000000000
0!
0&
#1005000000
1!
1&
b000000000000000000001100010 +
#1010000000
0!
0&
#1015000000
1!
1&
b000000000000000000001100011 +
#1020000000
0!
0&
#1025000000
1!
1&
b000000000000000000001100100 +
#1030000000
0!
0&
#1035000000
1!
1&
b000000000000000000001100101 +
#1040000000
0!
0&
#1045000000
1!
1&
b000000000000000000001100110 +
#1050000000
0!
0&
#1055000000
1!
1&
b000000000000000000001100111 +
#1060000000
0!
0&
#1065000000
1!
1&
b000000000000000000001101000 +
#1070000000
0!
0&
#1075000000
1!
1&
b000000000000000000001101001 +
#1080000000
0!
0&
#1085000000
1!
1&
b000000000000000000001101010 +
#1090000000
0!
0&
#1095000000
1!
1&
b000000000000000000001101011 +
#1100000000
0!
0&
#1105000000
1!
1&
b000000000000000000001101100 +
#1110000000
0!
0&
#1115000000
1!
1&
b000000000000000000001101101 +
#1120000000
0!
0&
#1125000000
1!
1&
b000000000000000000001101110 +
#1130000000
0!
0&
#1135000000
1!
1&
b000000000000000000001101111 +
#1140000000
0!
0&
#1145000000
1!
1&
b000000000000000000001110000 +
#1150000000
0!
0&
#1155000000
1!
1&
b000000000000000000001110001 +
#1160000000
0!
0&
#1165000000
1!
1&
b000000000000000000001110010 +
#1170000000
0!
0&
#1175000000
1!
1&
b000000000000000000001110011 +
#1180000000
0!
0&
#1185000000
1!
1&
b000000000000000000001110100 +
#1190000000
0!
0&
#1195000000
1!
1&
b000000000000000000001110101 +
#1200000000
0!
0&
#1205000000
1!
1&
b000000000000000000001110110 +
#1210000000
0!
0&
#1215000000
1!
1&
b000000000000000000001110111 +
#1220000000
0!
0&
#1225000000
1!
1&
b000000000000000000001111000 +
#1230000000
0!
0&
#1235000000
1!
1&
b000000000000000000001111001 +
#1240000000
0!
0&
#1245000000
1!
1&
b000000000000000000001111010 +
#1250000000
0!
0&
#1255000000
1!
1&
b000000000000000000001111011 +
#1260000000
0!
0&
#1265000000
1!
1&
b000000000000000000001111100 +
#1270000000
0!
0&
#1275000000
1!
1&
b000000000000000000001111101 +
#1280000000
0!
0&
#1285000000
1!
1&
b000000000000000000001111110 +
#1290000000
0!
0&
#1295000000
1!
1&
b000000000000000000001111111 +
#1300000000
0!
0&
#1305000000
1!
1&
b000000000000000000010000000 +
#1310000000
0!
0&
#1315000000
1!
1&
b000000000000000000010000001 +
#1320000000
0!
0&
#1325000000
1!
1&
b000000000000000000010000010 +
#1330000000
0!
0&
#1335000000
1!
1&
b000000000000000000010000011 +
#1340000000
0!
0&
#1345000000
1!
1&
b000000000000000000010000100 +
#1350000000
0!
0&
#1355000000
1!
1&
b000000000000000000010000101 +
#1360000000
0!
0&
#1365000000
1!
1&
b000000000000000000010000110 +
#1370000000
0!
0&
#1375000000
1!
1&
b000000000000000000010000111 +
#1380000000
0!
0&
#1385000000
1!
1&
b000000000000000000010001000 +
#1390000000
0!
0&
#1395000000
1!
1&
b000000000000000000010001001 +
#1400000000
0!
0&
#1405000000
1!
1&
b000000000000000000010001010 +
#1410000000
0!
0&
#1415000000
1!
1&
b000000000000000000010001011 +
#1420000000
0!
0&
#1425000000
1!
1&
b000000000000000000010001100 +
#1430000000
0!
0&
#1435000000
1!
1&
b000000000000000000010001101 +
#1440000000
0!
0&
#1445000000
1!
1&
b000000000000000000010001110 +
#1450000000
0!
0&
#1455000000
1!
1&
b000000000000000000010001111 +
#1460000000
0!
0&
#1465000000
1!
1&
b000000000000000000010010000 +
#1470000000
0!
0&
#1475000000
1!
1&
b000000000000000000010010001 +
#1480000000
0!
0&
#1485000000
1!
1&
b000000000000000000010010010 +
#1490000000
0!
0&
#1495000000
1!
1&
b000000000000000000010010011 +
#1500000000
0!
0&
#1505000000
1!
1&
b000000000000000000010010100 +
#1510000000
0!
0&
#1515000000
1!
1&
b000000000000000000010010101 +
#1520000000
0!
0&
#1525000000
1!
1&
b000000000000000000010010110 +
#1530000000
0!
0&
#1535000000
1!
1&
b000000000000000000010010111 +
#1540000000
0!
0&
#1545000000
1!
1&
b000000000000000000010011000 +
#1550000000
0!
0&
#1555000000
1!
1&
b000000000000000000010011001 +
#1560000000
0!
0&
#1565000000
1!
1&
b000000000000000000010011010 +
#1570000000
0!
0&
#1575000000
1!
1&
b000000000000000000010011011 +
#1580000000
0!
0&
#1585000000
1!
1&
b000000000000000000010011100 +
#1590000000
0!
0&
#1595000000
1!
1&
b000000000000000000010011101 +
#1600000000
0!
0&
#1605000000
1!
1&
b000000000000000000010011110 +
#1610000000
0!
0&
#1615000000
1!
1&
b000000000000000000010011111 +
#1620000000
0!
0&
#1625000000
1!
1&
b000000000000000000010100000 +
#1630000000
0!
0&
#1635000000
1!
1&
b000000000000000000010100001 +
#1640000000
0!
0&
#1645000000
1!
1&
b000000000000000000010100010 +
#1650000000
0!
0&
#1655000000
1!
1&
b000000000000000000010100011 +
#1660000000
0!
0&
#1665000000
1!
1&
b000000000000000000010100100 +
#1670000000
0!
0&
#1675000000
1!
1&
b000000000000000000010100101 +
#1680000000
0!
0&
#1685000000
1!
1&
b000000000000000000010100110 +
#1690000000
0!
0&
#1695000000
1!
1&
b000000000000000000010100111 +
#1700000000
0!
0&
#1705000000
1!
1&
b000000000000000000010101000 +
#1710000000
0!
0&
#1715000000
1!
1&
b000000000000000000010101001 +
#1720000000
0!
0&
#1725000000
1!
1&
b000000000000000000010101010 +
#1730000000
0!
0&
#1735000000
1!
1&
b000000000000000000010101011 +
#1740000000
0!
0&
#1745000000
1!
1&
b000000000000000000010101100 +
#1750000000
0!
0&
#1755000000
1!
1&
b000000000000000000010101101 +
#1760000000
0!
0&
#1765000000
1!
1&
b000000000000000000010101110 +
#1770000000
0!
0&
#1775000000
1!
1&
b000000000000000000010101111 +
#1780000000
0!
0&
#1785000000
1!
1&
b000000000000000000010110000 +
#1790000000
0!
0&
#1795000000
1!
1&
b000000000000000000010110001 +
#1800000000
0!
0&
#1805000000
1!
1&
b000000000000000000010110010 +
#1810000000
0!
0&
#1815000000
1!
1&
b000000000000000000010110011 +
#1820000000
0!
0&
#1825000000
1!
1&
b000000000000000000010110100 +
#1830000000
0!
0&
#1835000000
1!
1&
b000000000000000000010110101 +
#1840000000
0!
0&
#1845000000
1!
1&
b000000000000000000010110110 +
#1850000000
0!
0&
#1855000000
1!
1&
b000000000000000000010110111 +
#1860000000
0!
0&
#1865000000
1!
1&
b000000000000000000010111000 +
#1870000000
0!
0&
#1875000000
1!
1&
b000000000000000000010111001 +
#1880000000
0!
0&
#1885000000
1!
1&
b000000000000000000010111010 +
#1890000000
0!
0&
#1895000000
1!
1&
b000000000000000000010111011 +
#1900000000
0!
0&
#1905000000
1!
1&
b000000000000000000010111100 +
#1910000000
0!
0&
#1915000000
1!
1&
b000000000000000000010111101 +
#1920000000
0!
0&
#1925000000
1!
1&
b000000000000000000010111110 +
#1930000000
0!
0&
#1935000000
1!
1&
b000000000000000000010111111 +
#1940000000
0!
0&
#1945000000
1!
1&
b000000000000000000011000000 +
#1950000000
0!
0&
#1955000000
1!
1&
b000000000000000000011000001 +
#1960000000
0!
0&
#1965000000
1!
1&
b000000000000000000011000010 +
#1970000000
0!
0&
#1975000000
1!
1&
b000000000000000000011000011 +
#1980000000
0!
0&
#1985000000
1!
1&
b000000000000000000011000100 +
#1990000000
0!
0&
#1995000000
1!
1&
b000000000000000000011000101 +
#2000000000
0!
0&
#2005000000
1!
1&
b000000000000000000011000110 +
#2010000000
0!
0&
#2015000000
1!
1&
b000000000000000000011000111 +
#2020000000
0!
0&
#2025000000
1!
1&
b000000000000000000011001000 +
#2030000000
0!
0&
#2035000000
1!
1&
b000000000000000000011001001 +
#2040000000
0!
0&
#2045000000
1!
1&
b000000000000000000011001010 +
#2050000000
0!
0&
#2055000000
1!
1&
b000000000000000000011001011 +
#2060000000
0!
0&
#2065000000
1!
1&
b000000000000000000011001100 +
#2070000000
0!
0&
#2075000000
1!
1&
b000000000000000000011001101 +
#2080000000
0!
0&
#2085000000
1!
1&
b000000000000000000011001110 +
#2090000000
0!
0&
#2095000000
1!
1&
b000000000000000000011001111 +
#2100000000
0!
0&
#2105000000
1!
1&
b000000000000000000011010000 +
#2110000000
0!
0&
#2115000000
1!
1&
b000000000000000000011010001 +
#2120000000
0!
0&
#2125000000
1!
1&
b000000000000000000011010010 +
#2130000000
0!
0&
#2135000000
1!
1&
b000000000000000000011010011 +
#2140000000
0!
0&
#2145000000
1!
1&
b000000000000000000011010100 +
#2150000000
0!
0&
#2155000000
1!
1&
b000000000000000000011010101 +
#2160000000
0!
0&
#2165000000
1!
1&
b000000000000000000011010110 +
#2170000000
0!
0&
#2175000000
1!
1&
b000000000000000000011010111 +
#2180000000
0!
0&
#2185000000
1!
1&
b000000000000000000011011000 +
#2190000000
0!
0&
#2195000000
1!
1&
b000000000000000000011011001 +
#2200000000
0!
0&
#2205000000
1!
1&
b000000000000000000011011010 +
#2210000000
0!
0&
#2215000000
1!
1&
b000000000000000000011011011 +
#2220000000
0!
0&
#2225000000
1!
1&
b000000000000000000011011100 +
#2230000000
0!
0&
#2235000000
1!
1&
b000000000000000000011011101 +
#2240000000
0!
0&
#2245000000
1!
1&
b000000000000000000011011110 +
#2250000000
0!
0&
#2255000000
1!
1&
b000000000000000000011011111 +
#2260000000
0!
0&
#2265000000
1!
1&
b000000000000000000011100000 +
#2270000000
0!
0&
#2275000000
1!
1&
b000000000000000000011100001 +
#2280000000
0!
0&
#2285000000
1!
1&
b000000000000000000011100010 +
#2290000000
0!
0&
#2295000000
1!
1&
b000000000000000000011100011 +
#2300000000
0!
0&
#2305000000
1!
1&
b000000000000000000011100100 +
#2310000000
0!
0&
#2315000000
1!
1&
b000000000000000000011100101 +
#2320000000
0!
0&
#2325000000
1!
1&
b000000000000000000011100110 +
#2330000000
0!
0&
#2335000000
1!
1&
b000000000000000000011100111 +
#2340000000
0!
0&
#2345000000
1!
1&
b000000000000000000011101000 +
#2350000000
0!
0&
#2355000000
1!
1&
b000000000000000000011101001 +
#2360000000
0!
0&
#2365000000
1!
1&
b000000000000000000011101010 +
#2370000000
0!
0&
#2375000000
1!
1&
b000000000000000000011101011 +
#2380000000
0!
0&
#2385000000
1!
1&
b000000000000000000011101100 +
#2390000000
0!
0&
#2395000000
1!
1&
b000000000000000000011101101 +
#2400000000
0!
0&
#2405000000
1!
1&
b000000000000000000011101110 +
#2410000000
0!
0&
#2415000000
1!
1&
b000000000000000000011101111 +
#2420000000
0!
0&
#2425000000
1!
1&
b000000000000000000011110000 +
#2430000000
0!
0&
#2435000000
1!
1&
b000000000000000000011110001 +
#2440000000
0!
0&
#2445000000
1!
1&
b000000000000000000011110010 +
#2450000000
0!
0&
#2455000000
1!
1&
b000000000000000000011110011 +
#2460000000
0!
0&
#2465000000
1!
1&
b000000000000000000011110100 +
#2470000000
0!
0&
#2475000000
1!
1&
b000000000000000000011110101 +
#2480000000
0!
0&
#2485000000
1!
1&
b000000000000000000011110110 +
#2490000000
0!
0&
#2495000000
1!
1&
b000000000000000000011110111 +
#2500000000
0!
0&
#2505000000
1!
1&
b000000000000000000011111000 +
#2510000000
0!
0&
#2515000000
1!
1&
b000000000000000000011111001 +
#2520000000
0!
0&
#2525000000
1!
1&
b000000000000000000011111010 +
#2530000000
0!
0&
#2535000000
1!
1&
b000000000000000000011111011 +
#2540000000
0!
0&
#2545000000
1!
1&
b000000000000000000011111100 +
#2550000000
0!
0&
#2555000000
1!
1&
b000000000000000000011111101 +
#2560000000
0!
0&
#2565000000
1!
1&
b000000000000000000011111110 +
#2570000000
0!
0&
#2575000000
1!
1&
b000000000000000000011111111 +
#2580000000
0!
0&
#2585000000
1!
1&
b000000000000000000100000000 +
#2590000000
0!
0&
#2595000000
1!
1&
b000000000000000000100000001 +
#2600000000
0!
0&
#2605000000
1!
1&
b000000000000000000100000010 +
#2610000000
0!
0&
#2615000000
1!
1&
b000000000000000000100000011 +
#2620000000
0!
0&
#2625000000
1!
1&
b000000000000000000100000100 +
#2630000000
0!
0&
#2635000000
1!
1&
b000000000000000000100000101 +
#2640000000
0!
0&
#2645000000
1!
1&
b000000000000000000100000110 +
#2650000000
0!
0&
#2655000000
1!
1&
b000000000000000000100000111 +
#2660000000
0!
0&
#2665000000
1!
1&
b000000000000000000100001000 +
#2670000000
0!
0&
#2675000000
1!
1&
b000000000000000000100001001 +
#2680000000
0!
0&
#2685000000
1!
1&
b000000000000000000100001010 +
#2690000000
0!
0&
#2695000000
1!
1&
b000000000000000000100001011 +
#2700000000
0!
0&
#2705000000
1!
1&
b000000000000000000100001100 +
#2710000000
0!
0&
#2715000000
1!
1&
b000000000000000000100001101 +
#2720000000
0!
0&
#2725000000
1!
1&
b000000000000000000100001110 +
#2730000000
0!
0&
#2735000000
1!
1&
b000000000000000000100001111 +
#2740000000
0!
0&
#2745000000
1!
1&
b000000000000000000100010000 +
#2750000000
0!
0&
#2755000000
1!
1&
b000000000000000000100010001 +
#2760000000
0!
0&
#2765000000
1!
1&
b000000000000000000100010010 +
#2770000000
0!
0&
#2775000000
1!
1&
b000000000000000000100010011 +
#2780000000
0!
0&
#2785000000
1!
1&
b000000000000000000100010100 +
#2790000000
0!
0&
#2795000000
1!
1&
b000000000000000000100010101 +
#2800000000
0!
0&
#2805000000
1!
1&
b000000000000000000100010110 +
#2810000000
0!
0&
#2815000000
1!
1&
b000000000000000000100010111 +
#2820000000
0!
0&
#2825000000
1!
1&
b000000000000000000100011000 +
#2830000000
0!
0&
#2835000000
1!
1&
b000000000000000000100011001 +
#2840000000
0!
0&
#2845000000
1!
1&
b000000000000000000100011010 +
#2850000000
0!
0&
#2855000000
1!
1&
b000000000000000000100011011 +
#2860000000
0!
0&
#2865000000
1!
1&
b000000000000000000100011100 +
#2870000000
0!
0&
#2875000000
1!
1&
b000000000000000000100011101 +
#2880000000
0!
0&
#2885000000
1!
1&
b000000000000000000100011110 +
#2890000000
0!
0&
#2895000000
1!
1&
b000000000000000000100011111 +
#2900000000
0!
0&
#2905000000
1!
1&
b000000000000000000100100000 +
#2910000000
0!
0&
#2915000000
1!
1&
b000000000000000000100100001 +
#2920000000
0!
0&
#2925000000
1!
1&
b000000000000000000100100010 +
#2930000000
0!
0&
#2935000000
1!
1&
b000000000000000000100100011 +
#2940000000
0!
0&
#2945000000
1!
1&
b000000000000000000100100100 +
#2950000000
0!
0&
#2955000000
1!
1&
b000000000000000000100100101 +
#2960000000
0!
0&
#2965000000
1!
1&
b000000000000000000100100110 +
#2970000000
0!
0&
#2975000000
1!
1&
b000000000000000000100100111 +
#2980000000
0!
0&
#2985000000
1!
1&
b000000000000000000100101000 +
#2990000000
0!
0&
#2995000000
1!
1&
b000000000000000000100101001 +
#3000000000
0!
0&
#3005000000
1!
1&
b000000000000000000100101010 +
#3010000000
0!
0&
#3015000000
1!
1&
b000000000000000000100101011 +
#3020000000
0!
0&
#3025000000
1!
1&
b000000000000000000100101100 +
#3030000000
0!
0&
#3035000000
1!
1&
b000000000000000000100101101 +
#3040000000
0!
0&
#3045000000
1!
1&
b000000000000000000100101110 +
#3050000000
0!
0&
#3055000000
1!
1&
b000000000000000000100101111 +
#3060000000
0!
0&
#3065000000
1!
1&
b000000000000000000100110000 +
#3070000000
0!
0&
#3075000000
1!
1&
b000000000000000000100110001 +
#3080000000
0!
0&
#3085000000
1!
1&
b000000000000000000100110010 +
#3090000000
0!
0&
#3095000000
1!
1&
b000000000000000000100110011 +
#3100000000
0!
0&
#3105000000
1!
1&
b000000000000000000100110100 +
#3110000000
0!
0&
#3115000000
1!
1&
b000000000000000000100110101 +
#3120000000
0!
0&
#3125000000
1!
1&
b000000000000000000100110110 +
#3130000000
0!
0&
#3135000000
1!
1&
b000000000000000000100110111 +
#3140000000
0!
0&
#3145000000
1!
1&
b000000000000000000100111000 +
#3150000000
0!
0&
#3155000000
1!
1&
b000000000000000000100111001 +
#3160000000
0!
0&
#3165000000
1!
1&
b000000000000000000100111010 +
#3170000000
0!
0&
#3175000000
1!
1&
b000000000000000000100111011 +
#3180000000
0!
0&
#3185000000
1!
1&
b000000000000000000100111100 +
#3190000000
0!
0&
#3195000000
1!
1&
b000000000000000000100111101 +
#3200000000
0!
0&
#3205000000
1!
1&
b000000000000000000100111110 +
#3210000000
0!
0&
#3215000000
1!
1&
b000000000000000000100111111 +
#3220000000
0!
0&
#3225000000
1!
1&
b000000000000000000101000000 +
#3230000000
0!
0&
#3235000000
1!
1&
b000000000000000000101000001 +
#3240000000
0!
0&
#3245000000
1!
1&
b000000000000000000101000010 +
#3250000000
0!
0&
#3255000000
1!
1&
b000000000000000000101000011 +
#3260000000
0!
0&
#3265000000
1!
1&
b000000000000000000101000100 +
#3270000000
0!
0&
#3275000000
1!
1&
b000000000000000000101000101 +
#3280000000
0!
0&
#3285000000
1!
1&
b000000000000000000101000110 +
#3290000000
0!
0&
#3295000000
1!
1&
b000000000000000000101000111 +
#3300000000
0!
0&
#3305000000
1!
1&
b000000000000000000101001000 +
#3310000000
0!
0&
#3315000000
1!
1&
b000000000000000000101001001 +
#3320000000
0!
0&
#3325000000
1!
1&
b000000000000000000101001010 +
#3330000000
0!
0&
#3335000000
1!
1&
b000000000000000000101001011 +
#3340000000
0!
0&
#3345000000
1!
1&
b000000000000000000101001100 +
#3350000000
0!
0&
#3355000000
1!
1&
b000000000000000000101001101 +
#3360000000
0!
0&
#3365000000
1!
1&
b000000000000000000101001110 +
#3370000000
0!
0&
#3375000000
1!
1&
b000000000000000000101001111 +
#3380000000
0!
0&
#3385000000
1!
1&
b000000000000000000101010000 +
#3390000000
0!
0&
#3395000000
1!
1&
b000000000000000000101010001 +
#3400000000
0!
0&
#3405000000
1!
1&
b000000000000000000101010010 +
#3410000000
0!
0&
#3415000000
1!
1&
b000000000000000000101010011 +
#3420000000
0!
0&
#3425000000
1!
1&
b000000000000000000101010100 +
#3430000000
0!
0&
#3435000000
1!
1&
b000000000000000000101010101 +
#3440000000
0!
0&
#3445000000
1!
1&
b000000000000000000101010110 +
#3450000000
0!
0&
#3455000000
1!
1&
b000000000000000000101010111 +
#3460000000
0!
0&
#3465000000
1!
1&
b000000000000000000101011000 +
#3470000000
0!
0&
#3475000000
1!
1&
b000000000000000000101011001 +
#3480000000
0!
0&
#3485000000
1!
1&
b000000000000000000101011010 +
#3490000000
0!
0&
