buffer_ual/buffer_ual.vhd
library IEEE;
use IEEE.std_logic_1164.all;

entity buffer_ual is
generic (
    N : integer := 4  
);
port (
	e1 : in std_logic_vector (N-1 downto 0);
    reset : in std_logic;
   
    clock : in std_logic;

    enable : in std_logic;
    s1 : out std_logic_vector (N-1 downto 0)
    
);
end  buffer_ual; 

architecture buffer_ual_arch of buffer_ual is

begin

    process(clock, reset)
    begin
        -- Reset asynchrone sur niveau haut
        if reset = '1' then
            s1 <= (others => '0');
        elsif rising_edge(clock) and enable ='1' then
                s1 <= e1;
        end if;

    end process;

end buffer_ual_arch;

buffer_ual/buffer_ual_testbench.vhd
library ieee;
use ieee.std_logic_1164.all;
use ieee.numeric_std.all;
entity buffer_ual_tb is
end buffer_ual_tb;

architecture tb_arch of buffer_ual_tb is

    component buffer_ual
        generic (N : integer := 4);
        port (
            e1     : in  std_logic_vector(N-1 downto 0);
            reset  : in  std_logic;
            clock  : in  std_logic;
            enable : in  std_logic;
            s1     : out std_logic_vector(N-1 downto 0)
        );
    end component;

    signal clk_sim    : std_logic := '0';
    signal reset_sim    : std_logic := '0';
    signal enable_sim1    : std_logic := '1';
    signal enable_sim2    : std_logic := '0';
    signal e_sim1    : std_logic_vector(3 downto 0) := (others => '0');
    signal e_sim2    : std_logic_vector(2 downto 0) := (others => '0');
    signal s1_sim1   : std_logic_vector(3 downto 0);
    signal s1_sim2   : std_logic_vector(2 downto 0);

begin

    -- Buffer avec enable actif
    buf1 : buffer_ual
        generic map (N => 4)
        port map (
            e1     => e_sim1,
            reset  => reset_sim,
            clock  => clk_sim,
            enable => '1',
            s1     => s1_sim1
        );

    -- Buffer avec enable inactif
    buf2 : buffer_ual
        generic map (N => 3)
        port map (
            e1     => e_sim2,
            reset  => reset_sim,
            clock  => clk_sim,
            enable => enable_sim2,
            s1     => s1_sim2
        );

    -- Génération de l'horloge
    clk_process : process
    begin
        while now < 200 ns loop
            clk_sim <= '0'; wait for 5 ns;
            clk_sim <= '1'; wait for 5 ns;
        end loop;
        wait;
    end process;

    -- Stimulus
    stim_proc : process
    begin
       
        report "Buffer 4 bits sans enable : " severity note;

        -- Test buffer avec enable actif
        e_sim1 <= "1010";
        wait for 10 ns;
        report "e1_sim:" & integer'image(to_integer(unsigned(e_sim1))) severity note;
        report "s1_sim1: " & integer'image(to_integer(unsigned(s1_sim1))) severity note;

        e_sim1 <= "0101";
        wait for 10 ns;
        report "e1_sim:" & integer'image(to_integer(unsigned(e_sim1))) severity note;
        report "s1_sim1: " & integer'image(to_integer(unsigned(s1_sim1))) severity note;

        report "-------------------------------" severity note;
        -- Test buffer avec enable inactif (doit rester à 0)
        report "Buffer 3 bits avec enable : " severity note;
        e_sim2 <= "111";
         report "e2_sim:" & integer'image(to_integer(unsigned(e_sim2))) severity note;
        report "s2_sim1: " & integer'image(to_integer(unsigned(s1_sim2))) severity note;

        wait for 10 ns;
        e_sim2 <= "001";
        wait for 10 ns;
        report "e2_sim:" & integer'image(to_integer(unsigned(e_sim2))) severity note;
        report "Valeur de s1_sim2: " & integer'image(to_integer(unsigned(s1_sim2)))  severity note;
        
        report ">>> Activation de enable ! "severity note;
        -- Désactive enable sur buf1, la sortie doit rester inchangée
        enable_sim2 <= '1';
        e_sim2 <= "111";
        wait for 10 ns;
        enable_sim2 <= '0';
        report "e2_sim:" & integer'image(to_integer(unsigned(e_sim2))) severity note;
        report "Valeur de s1_sim2 après activation enable: " & integer'image(to_integer(unsigned(s1_sim2))) severity note;
       
        wait for 10 ns;

        report ">>> Remodification de la valeur sans activer enable ! "severity note;
        wait for 10 ns;
        e_sim2 <= "001";
        wait for 10 ns;
        report "e2_sim:" & integer'image(to_integer(unsigned(e_sim2))) severity note;
        report "Valeur de s1_sim2: " & integer'image(to_integer(unsigned(s1_sim2)))  severity note;

        wait for 10 ns;
       wait;
    end process;

end tb_arch;

buffer_ual/buffer_ual_gtkwave.vcd
$date
  Sat May 31 14:50:21 2025
$end
$version
  GHDL v0
$end
$timescale
  1 fs
$end
$scope module standard $end
$upscope $end
$scope module std_logic_1164 $end
$upscope $end
$scope module numeric_std $end
$upscope $end
$scope module buffer_ual_tb $end
$var reg 1 ! clk_sim $end
$var reg 1 " reset_sim $end
$var reg 1 # enable_sim1 $end
$var reg 1 $ enable_sim2 $end
$var reg 4 % e_sim1[3:0] $end
$var reg 3 & e_sim2[2:0] $end
$var reg 4 ' s1_sim1[3:0] $end
$var reg 3 ( s1_sim2[2:0] $end
$scope module buf1 $end
$var reg 4 ) e1[3:0] $end
$var reg 1 * reset $end
$var reg 1 + clock $end
$var reg 1 , enable $end
$var reg 4 - s1[3:0] $end
$upscope $end
$scope module buf2 $end
$var reg 3 . e1[2:0] $end
$var reg 1 / reset $end
$var reg 1 0 clock $end
$var reg 1 1 enable $end
$var reg 3 2 s1[2:0] $end
$upscope $end
$upscope $end
$enddefinitions $end
#0
0!
0"
1#
0$
b1010 %
b000 &
bUUUU '
bUUU (
b1010 )
0*
0+
1,
bUUUU -
b000 .
0/
00
01
bUUU 2
#5000000
1!
b1010 '
1+
b1010 -
10
#10000000
0!
b0101 %
b0101 )
0+
00
#15000000
1!
b0101 '
1+
b0101 -
10
#20000000
0!
b111 &
0+
b111 .
00
#25000000
1!
1+
10
#30000000
0!
b001 &
0+
b001 .
00
#35000000
1!
1+
10
#40000000
0!
1$
b111 &
0+
b111 .
00
11
#45000000
1!
b111 (
1+
10
b111 2
#50000000
0!
0$
0+
00
01
#55000000
1!
1+
10
#60000000
0!
0+
00
#65000000
1!
1+
10
#70000000
0!
b001 &
0+
b001 .
00
