Partie_jeu/verif_resultat/verif_resultat.vhd
library ieee;
use ieee.std_logic_1164.all;

entity verif_resultat is
    port (
        clk       : in  std_logic; -- horloge système
        reset     : in  std_logic; -- réinitialisation du module
        timeout   : in  std_logic; -- signal de fin de délai
        led_color : in  std_logic_vector(2 downto 0); -- couleur affichée sur LD3 (3 bits, R=100, G=010, B=001)
        btn_r     : in  std_logic; -- boutons de réponse (BTN1, BTN2, BTN3)
        btn_g     : in  std_logic;
        btn_b     : in  std_logic;
        valid_hit : out std_logic -- passe à '1' si la bonne réponse a été donnée dans les temps
    );
end verif_resultat;

architecture verif_resultat_arch of verif_resultat is
    signal user_pressed : std_logic := '0';
    signal valid_hit_reg : std_logic := '0';
begin
    process(clk, reset)
    begin
        if reset = '1' or timeout = '1' then
            user_pressed <= '0';
            valid_hit_reg <= '0';
        elsif rising_edge(clk) then
            if user_pressed = '0' then
                if led_color = "100" and btn_r = '1' then
                    valid_hit_reg <= '1';
                    user_pressed <= '1';
                elsif led_color = "010" and btn_g = '1' then
                    valid_hit_reg <= '1';
                    user_pressed <= '1';
                elsif led_color = "001" and btn_b = '1' then
                    valid_hit_reg <= '1';
                    user_pressed <= '1';
                else
                    valid_hit_reg <= '0';
                end if;
            else
                valid_hit_reg <= '0';
            end if;
        end if;
    end process;
    valid_hit <= valid_hit_reg;
end verif_resultat_arch;

Partie_jeu/verif_resultat/verif_resultat_testbench.vhd
library ieee;
use ieee.std_logic_1164.all;

entity verif_resultat_tb is
end verif_resultat_tb;

architecture verif_resultat_tb_arch of verif_resultat_tb is
    signal clk_sim       : std_logic := '0';
    signal reset_sim     : std_logic := '0';
    signal timeout_sim   : std_logic := '0';
    signal led_color_sim : std_logic_vector(2 downto 0) := "000";
    signal btn_r_sim     : std_logic := '0';
    signal btn_g_sim     : std_logic := '0';
    signal btn_b_sim     : std_logic := '0';
    signal valid_hit_sim : std_logic;

    component verif_resultat
        port (
            clk       : in  std_logic;
            reset     : in  std_logic;
            timeout   : in  std_logic;
            led_color : in  std_logic_vector(2 downto 0);
            btn_r     : in  std_logic;
            btn_g     : in  std_logic;
            btn_b     : in  std_logic;
            valid_hit : out std_logic
        );
    end component;

    function slv_to_str(slv : std_logic_vector) return string is
        variable result : string(1 to slv'length);
    begin
        for i in slv'range loop
            result(i - slv'low + 1) := character'VALUE(std_ulogic'image(slv(i)));
        end loop;
        return result;
    end function;
begin
    verif_resultat_inst: verif_resultat
        port map (
            clk       => clk_sim,
            reset     => reset_sim,
            timeout   => timeout_sim,
            led_color => led_color_sim,
            btn_r     => btn_r_sim,
            btn_g     => btn_g_sim,
            btn_b     => btn_b_sim,
            valid_hit => valid_hit_sim
        );

    -- Clock generation
    clk_process: process
    begin
        while now < 400 ns loop
            clk_sim <= '0'; wait for 5 ns;
            clk_sim <= '1'; wait for 5 ns;
        end loop;
        wait;
    end process;

    -- Stimulus principal
    test_proc: process
    begin
        -- Reset global
        reset_sim <= '1'; timeout_sim <= '0';
        btn_r_sim <= '0'; btn_g_sim <= '0'; btn_b_sim <= '0';
        wait for 10 ns;
        reset_sim <= '0';
        wait for 10 ns;

        --  Bon bouton 
            led_color_sim <= "100"; btn_r_sim <= '0'; btn_g_sim <= '0'; btn_b_sim <= '0'; timeout_sim <= '0';
            wait for 10 ns;
            btn_r_sim <= '1';
            wait for 10 ns;
            btn_r_sim <= '0';
            wait for 20 ns;

            --  Mauvaise réponse 
            led_color_sim <= "001"; btn_r_sim <= '0'; btn_g_sim <= '1'; btn_b_sim <= '0'; timeout_sim <= '0';
            wait for 10 ns;
            btn_g_sim <= '0';
            wait for 20 ns;

            -- Timeout 
            led_color_sim <= "010"; btn_r_sim <= '0'; btn_g_sim <= '0'; btn_b_sim <= '0'; timeout_sim <= '0';
            wait for 10 ns;
            timeout_sim <= '1';
            wait for 10 ns;
            timeout_sim <= '0';
            wait for 20 ns;

            -- Bonne réponse 
            led_color_sim <= "001"; btn_r_sim <= '0'; btn_g_sim <= '0'; btn_b_sim <= '0'; timeout_sim <= '0';
            wait for 10 ns;
            btn_b_sim <= '1';
            wait for 10 ns;
            btn_b_sim <= '0';
           

        wait;
    end process;

    -- Affichage
    monitor: process(clk_sim)
    begin
        if rising_edge(clk_sim) then
            report "t=" & time'image(now) &
                   " | led_color=" & slv_to_str(led_color_sim) &
                   " | btn_r=" & std_logic'image(btn_r_sim) &
                   " | btn_g=" & std_logic'image(btn_g_sim) &
                   " | btn_b=" & std_logic'image(btn_b_sim) &
                   " | timeout=" & std_logic'image(timeout_sim) &
                   " | valid_hit=" & std_logic'image(valid_hit_sim);
        end if;
    end process;

end verif_resultat_tb_arch;

Partie_jeu/verif_resultat/verif_resultat_gtkwave.vcd
$date
  Thu May 29 17:00:02 2025
$end
$version
  GHDL v0
$end
$timescale
  1 fs
$end
$scope module standard $end
$upscope $end
$scope module std_logic_1164 $end
$upscope $end
$scope module verif_resultat_tb $end
$var reg 1 ! clk_sim $end
$var reg 1 " reset_sim $end
$var reg 1 # timeout_sim $end
$var reg 3 $ led_color_sim[2:0] $end
$var reg 1 % btn_r_sim $end
$var reg 1 & btn_g_sim $end
$var reg 1 ' btn_b_sim $end
$var reg 1 ( valid_hit_sim $end
$scope module verif_resultat_inst $end
$var reg 1 ) clk $end
$var reg 1 * reset $end
$var reg 1 + timeout $end
$var reg 3 , led_color[2:0] $end
$var reg 1 - btn_r $end
$var reg 1 . btn_g $end
$var reg 1 / btn_b $end
$var reg 1 0 valid_hit $end
$var reg 1 1 user_pressed $end
$var reg 1 2 valid_hit_reg $end
$upscope $end
$upscope $end
$enddefinitions $end
#0
0!
1"
0#
b000 $
0%
0&
0'
0(
0)
1*
0+
b000 ,
0-
0.
0/
00
01
02
#5000000
1!
1)
#10000000
0!
0"
0)
0*
#15000000
1!
1)
#20000000
0!
b100 $
0)
b100 ,
#25000000
1!
1)
#30000000
0!
1%
0)
1-
#35000000
1!
1(
1)
10
11
12
#40000000
0!
0%
0)
0-
#45000000
1!
0(
1)
00
02
#50000000
0!
0)
#55000000
1!
1)
#60000000
0!
b001 $
1&
0)
b001 ,
1.
#65000000
1!
1)
#70000000
0!
0&
0)
0.
#75000000
1!
1)
#80000000
0!
0)
#85000000
1!
1)
#90000000
0!
b010 $
0)
b010 ,
#95000000
1!
1)
#100000000
0!
1#
0)
1+
01
#105000000
1!
1)
#110000000
0!
0#
0)
0+
#115000000
1!
1)
#120000000
0!
0)
#125000000
1!
1)
#130000000
0!
b001 $
0)
b001 ,
#135000000
1!
1)
#140000000
0!
1'
0)
1/
#145000000
1!
1(
1)
10
11
12
#150000000
0!
0'
0)
0/
#155000000
1!
0(
1)
00
02
