LFSR/LFSR.vhd
library ieee;
use ieee.std_logic_1164.all;

-- Objectif :
-- Synthétiser puis simuler un registre à décalage à rétroaction linéaire (LFSR) sur 4 bits basé sur le polynôme :
-- X4 + X3 + 1
-- Ce LFSR génère une valeur pseudo-aléatoire à chaque exécution, qui pourra être utilisée comme stimulus couleur (ex : modulo 3 pour obtenir rouge, vert ou bleu).

entity lfsr is
    port(
        CLK100MHZ : in std_logic;  -- horloge principale (100 MHz)
        reset : in std_logic;  -- réinitialisation du registre à une valeur initiale non nulle «1011»
        enable : in std_logic;  -- active l’évolution du LFSR à chaque front montant
        rnd : out std_logic_vector(3 downto 0)  -- vecteur de 4 bits représentant la valeur pseudo-aléatoire courante
    );
    end lfsr;
architecture lfsr_arch of lfsr is
    signal resultat : std_logic_vector(3 downto 0) := "1011";
begin
    process(CLK100MHZ, reset)
    begin
        if reset = '1' then
            resultat <= "1011"; 
        elsif rising_edge(CLK100MHZ) then
            if enable = '1' then
                 resultat <= resultat(2 downto 0) & (resultat(3) xor resultat(2));
            end if;
        end if;
    end process;
    rnd <= resultat;
end lfsr_arch;

Partie_jeu/lfsr/lfsr_testbench.vhd


library ieee;
use ieee.std_logic_1164.all;
use ieee.numeric_std.all;

entity lfsr_tb is
end lfsr_tb;

architecture lfsr_tb_arch of lfsr_tb is
    signal clk_sim    : std_logic := '0';
    signal reset_sim  : std_logic := '0';
    signal enable_sim : std_logic := '0';
    signal rnd_sim    : std_logic_vector(3 downto 0);

    component lfsr
        port (
            CLK100MHZ : in std_logic;
            reset     : in std_logic;
            enable    : in std_logic;
            rnd       : out std_logic_vector(3 downto 0)
        );
    end component;
begin

    lfsr_inst: lfsr
        port map (
            CLK100MHZ => clk_sim,
            reset     => reset_sim,
            enable    => enable_sim,
            rnd       => rnd_sim
        );

   clk_process: process
    begin
        while now < 5000 ns loop
            clk_sim <= '0'; wait for 5 ns;
            clk_sim <= '1'; wait for 5 ns;
        end loop;
        wait;
    end process;

    process_lfsr: process
    begin

 
        reset_sim <= '1';
        enable_sim <= '0';
        wait for 20 ns;


        reset_sim <= '0';
        enable_sim <= '1';

        wait for 300 ns;

        enable_sim <= '0';
        wait for 20 ns;

        reset_sim <= '1';
        enable_sim <= '0';
        wait for 20 ns;
        reset_sim <= '0';
        enable_sim <= '1';

        wait for 300 ns;

        enable_sim <= '0';
        wait for 20 ns;

        wait;
    end process;
  affichage: process(clk_sim)
    begin
        if rising_edge(clk_sim) and enable_sim = '1' then
            report "rnd = " & integer'image(to_integer(unsigned(rnd_sim)));
        end if;
end process;

end lfsr_tb_arch;

Partie_jeu/lfsr/lfsr_gtkwave.vcd
$date
  Thu May 29 21:01:37 2025
$end
$version
  GHDL v0
$end
$timescale
  1 fs
$end
$scope module standard $end
$upscope $end
$scope module std_logic_1164 $end
$upscope $end
$scope module numeric_std $end
$upscope $end
$scope module lfsr_tb $end
$var reg 1 ! clk_sim $end
$var reg 1 " reset_sim $end
$var reg 1 # enable_sim $end
$var reg 4 $ rnd_sim[3:0] $end
$scope module lfsr_inst $end
$var reg 1 % clk100mhz $end
$var reg 1 & reset $end
$var reg 1 ' enable $end
$var reg 4 ( rnd[3:0] $end
$var reg 4 ) resultat[3:0] $end
$upscope $end
$upscope $end
$enddefinitions $end
#0
0!
1"
0#
b1011 $
0%
1&
0'
b1011 (
b1011 )
#5000000
1!
1%
#10000000
0!
0%
#15000000
1!
1%
#20000000
0!
0"
1#
0%
0&
1'
#25000000
1!
b0111 $
1%
b0111 (
b0111 )
#30000000
0!
0%
#35000000
1!
b1111 $
1%
b1111 (
b1111 )
#40000000
0!
0%
#45000000
1!
b1110 $
1%
b1110 (
b1110 )
#50000000
0!
0%
#55000000
1!
b1100 $
1%
b1100 (
b1100 )
#60000000
0!
0%
#65000000
1!
b1000 $
1%
b1000 (
b1000 )
#70000000
0!
0%
#75000000
1!
b0001 $
1%
b0001 (
b0001 )
#80000000
0!
0%
#85000000
1!
b0010 $
1%
b0010 (
b0010 )
#90000000
0!
0%
#95000000
1!
b0100 $
1%
b0100 (
b0100 )
#100000000
0!
0%
#105000000
1!
b1001 $
1%
b1001 (
b1001 )
#110000000
0!
0%
#115000000
1!
b0011 $
1%
b0011 (
b0011 )
#120000000
0!
0%
#125000000
1!
b0110 $
1%
b0110 (
b0110 )
#130000000
0!
0%
#135000000
1!
b1101 $
1%
b1101 (
b1101 )
#140000000
0!
0%
#145000000
1!
b1010 $
1%
b1010 (
b1010 )
#150000000
0!
0%
#155000000
1!
b0101 $
1%
b0101 (
b0101 )
#160000000
0!
0%
#165000000
1!
b1011 $
1%
b1011 (
b1011 )
#170000000
0!
0%
#175000000
1!
b0111 $
1%
b0111 (
b0111 )
#180000000
0!
0%
#185000000
1!
b1111 $
1%
b1111 (
b1111 )
#190000000
0!
0%
#195000000
1!
b1110 $
1%
b1110 (
b1110 )
#200000000
0!
0%
#205000000
1!
b1100 $
1%
b1100 (
b1100 )
#210000000
0!
0%
#215000000
1!
b1000 $
1%
b1000 (
b1000 )
#220000000
0!
0%
#225000000
1!
b0001 $
1%
b0001 (
b0001 )
#230000000
0!
0%
#235000000
1!
b0010 $
1%
b0010 (
b0010 )
#240000000
0!
0%
#245000000
1!
b0100 $
1%
b0100 (
b0100 )
#250000000
0!
0%
#255000000
1!
b1001 $
1%
b1001 (
b1001 )
#260000000
0!
0%
#265000000
1!
b0011 $
1%
b0011 (
b0011 )
#270000000
0!
0%
#275000000
1!
b0110 $
1%
b0110 (
b0110 )
#280000000
0!
0%
#285000000
1!
b1101 $
1%
b1101 (
b1101 )
#290000000
0!
0%
#295000000
1!
b1010 $
1%
b1010 (
b1010 )
#300000000
0!
0%
#305000000
1!
b0101 $
1%
b0101 (
b0101 )
#310000000
0!
0%
#315000000
1!
b1011 $
1%
b1011 (
b1011 )
#320000000
0!
0#
0%
0'
#325000000
1!
1%
#330000000
0!
0%
#335000000
1!
1%
#340000000
0!
1"
0%
1&
#345000000
1!
1%
#350000000
0!
0%
#355000000
1!
1%
#360000000
0!
0"
1#
0%
0&
1'
#365000000
1!
b0111 $
1%
b0111 (
b0111 )
#370000000
0!
0%
#375000000
1!
b1111 $
1%
b1111 (
b1111 )
#380000000
0!
0%
#385000000
1!
b1110 $
1%
b1110 (
b1110 )
#390000000
0!
0%
#395000000
1!
b1100 $
1%
b1100 (
b1100 )
#400000000
0!
0%
#405000000
1!
b1000 $
1%
b1000 (
b1000 )
#410000000
0!
0%
#415000000
1!
b0001 $
1%
b0001 (
b0001 )
#420000000
0!
0%
#425000000
1!
b0010 $
1%
b0010 (
b0010 )
#430000000
0!
0%
#435000000
1!
b0100 $
1%
b0100 (
b0100 )
#440000000
0!
0%
#445000000
1!
b1001 $
1%
b1001 (
b1001 )
#450000000
0!
0%
#455000000
1!
b0011 $
1%
b0011 (
b0011 )
#460000000
0!
0%
#465000000
1!
b0110 $
1%
b0110 (
b0110 )
#470000000
0!
0%
#475000000
1!
b1101 $
1%
b1101 (
b1101 )
#480000000
0!
0%
#485000000
1!
b1010 $
1%
b1010 (
b1010 )
#490000000
0!
0%
#495000000
1!
b0101 $
1%
b0101 (
b0101 )
#500000000
0!
0%
#505000000
1!
b1011 $
1%
b1011 (
b1011 )
#510000000
0!
0%
#515000000
1!
b0111 $
1%
b0111 (
b0111 )
#520000000
0!
0%
#525000000
1!
b1111 $
1%
b1111 (
b1111 )
#530000000
0!
0%
#535000000
1!
b1110 $
1%
b1110 (
b1110 )
#540000000
0!
0%
#545000000
1!
b1100 $
1%
b1100 (
b1100 )
#550000000
0!
0%
#555000000
1!
b1000 $
1%
b1000 (
b1000 )
#560000000
0!
0%
#565000000
1!
b0001 $
1%
b0001 (
b0001 )
#570000000
0!
0%
#575000000
1!
b0010 $
1%
b0010 (
b0010 )
#580000000
0!
0%
#585000000
1!
b0100 $
1%
b0100 (
b0100 )
#590000000
0!
0%
#595000000
1!
b1001 $
1%
b1001 (
b1001 )
#600000000
0!
0%
#605000000
1!
b0011 $
1%
b0011 (
b0011 )
#610000000
0!
0%
#615000000
1!
b0110 $
1%
b0110 (
b0110 )
#620000000
0!
0%
#625000000
1!
b1101 $
1%
b1101 (
b1101 )
#630000000
0!
0%
#635000000
1!
b1010 $
1%
b1010 (
b1010 )
#640000000
0!
0%
#645000000
1!
b0101 $
1%
b0101 (
b0101 )
#650000000
0!
0%
#655000000
1!
b1011 $
1%
b1011 (
b1011 )
#660000000
0!
0#
0%
0'
